threedi_urban_eia_nl/__init__.py
threedi_urban_eia_nl/process_results.py
threedi_urban_eia_nl/rain_series_simulations.py
threedi_urban_eia_nl-0.0.5.dist-info/licenses/LICENSE
threedi_urban_eia_nl-0.0.5.dist-info/METADATA
threedi_urban_eia_nl-0.0.5.dist-info/WHEEL
threedi_urban_eia_nl-0.0.5.dist-info/entry_points.txt
threedi_urban_eia_nl-0.0.5.dist-info/top_level.txt
threedi_urban_eia_nl-0.0.5.dist-info/RECORD
